ps_mem.py
ps_mem-3.14.dist-info/LICENSE
ps_mem-3.14.dist-info/METADATA
ps_mem-3.14.dist-info/WHEEL
ps_mem-3.14.dist-info/entry_points.txt
ps_mem-3.14.dist-info/pbr.json
ps_mem-3.14.dist-info/top_level.txt
ps_mem-3.14.dist-info/RECORD
