Metadata-Version: 2.1
Name: ps_mem
Version: 3.14
Summary: A utility to report core memory usage per program
Home-page: http://github.com/pixelb/ps_mem
Author: Pádraig Brady
Author-email: P@draigBrady.com
License: LGPLv2
Keywords: memory RAM profile program linux
Platform: UNKNOWN
Classifier: Development Status :: 5 - Production/Stable
Classifier: Topic :: Utilities
Classifier: Topic :: System :: Systems Administration
Classifier: License :: OSI Approved :: GNU Lesser General Public License v2 (LGPLv2)
Classifier: Programming Language :: Python
